openc2/__init__.py
openc2/base.py
openc2/core.py
openc2/custom.py
openc2/properties.py
openc2/version.py
openc2/v10/__init__.py
openc2/v10/actuators.py
openc2/v10/args.py
openc2/v10/common.py
openc2/v10/message.py
openc2/v10/slpf.py
openc2/v10/targets.py
openc2-1.0.0.dist-info/LICENSE
openc2-1.0.0.dist-info/METADATA
openc2-1.0.0.dist-info/WHEEL
openc2-1.0.0.dist-info/top_level.txt
openc2-1.0.0.dist-info/RECORD
