Metadata-Version: 2.1
Name: openc2
Version: 1.0.0
Summary: Produce and consume OpenC2 JSON messages
Home-page: UNKNOWN
License: MIT
Platform: UNKNOWN
Requires-Dist: six
Requires-Dist: stix2
